cmon/__init__.py
cmon/cli.py
cmon-0.1.0.dist-info/LICENSE
cmon-0.1.0.dist-info/METADATA
cmon-0.1.0.dist-info/WHEEL
cmon-0.1.0.dist-info/entry_points.txt
cmon-0.1.0.dist-info/top_level.txt
cmon-0.1.0.dist-info/RECORD
